{
    "batch": {
        "application": [{
            "id": "test1",
            "descriptive": {
                "name": "test1",
                "appVersion": "",
                "executablepathcontains": "",
                "framecontains": "",
                "icon": "",
                "jvmlocation": "",
                "launchwith": "",
                "manufacturer": "",
                "md5": "",
                "openIn": "",
                "processcontains": "",
                "titlebarcontains": "",
                "type": "",
                "urlcontains": "",
                "version": ""
            }
        }],
        "manufacturer": [],
        "field": [{
            "id": "test1",
            "descriptive": {
                "id": "test1",
                "name": "test1",
                "application": "test1",
                "actions": [
                    "",
                    ""
                ],
                "image": "",
                "offset": {},
                "path": "",
                "variablename": "",
                "version": ""
            }
        }],
        "table": [{
            "id": "test1",
            "name": "test1",
            "descriptive": {
                "csv": "",
                "name": "test1"
            }
        }],
        "flow": [{
            "id": "test1",
            "descriptive": {
                "application": "test1",
                "id": "test1",
                "name": "test1",
                "inputs": [],
                "outputs": [],
                "code": "const hey = 'hey'",
                "blocklyXml": "",
                "type": "",
                "anchors": [],
                "usesfields": [],
                "usesFlows": [],
                "usesTables": [],
                "compatibleVersion": "",
                "hideFromUser": false,
                "precompile": false,
                "restoreFocus": false,
                "isMandatory": false,
                "autocompleteSnippets": false,
                "autocompleteTypes": false,
                "debuggerEnabled": false,
                "hideInFlowLaunchMenu": false,
                "icon": "",
                "version": ""
            }
        }]
    }
}